si_wg_docgen/__init__.py
si_wg_docgen/bin/__init__.py
si_wg_docgen/bin/make_docx.py
si_wg_docgen/data/template.docx
si_wg_docgen/md2word.py
si_wg_docgen/md2word_styles.py
si_wg_docgen/ttl2md.py
si_wg_docgen-0.1.4.dist-info/entry_points.txt
si_wg_docgen-0.1.4.dist-info/LICENSE
si_wg_docgen-0.1.4.dist-info/WHEEL
si_wg_docgen-0.1.4.dist-info/METADATA
si_wg_docgen-0.1.4.dist-info/RECORD
